LICENSE
MANIFEST
MANIFEST.in
README.rst
requirements.txt
setup.cfg
setup.py
true_encoding/__init__.py
true_encoding/debug.py
true_encoding.egg-info/PKG-INFO
true_encoding.egg-info/SOURCES.txt
true_encoding.egg-info/dependency_links.txt
true_encoding.egg-info/not-zip-safe
true_encoding.egg-info/top_level.txt